{
    "data": {
        "definition": {
            "drawLayer": {
                "background": {
                    "payload": {
                        "index": 0.1
                    }
                },
                "pc": {
                    "payload": {
                        "index": 2
                    }
                },
                "ui": {
                    "payload": {
                        "index": 999
                    }
                }
            },
            "worldViewSetting": {
                "playableBox": {
                    "payload": {
                        "widthRatio": 1,
                        "heightRatio": 1,
                        "maxWidth": 900,
                        "maxHeight": 900,
                        "horizontalAlign": "center",
                        "verticalAlign": "center"
                    }
                },
                "backgroundImage": {
                    "payload": {
                        "playableCutoutWidth": 900,
                        "playableCutoutHeight": 900
                    }
                }
            }
        }
    }
}